makesignin/__init__.py
makesignin/me.py
makeSignIn-1.0.0.dist-info/LICENSE
makeSignIn-1.0.0.dist-info/METADATA
makeSignIn-1.0.0.dist-info/WHEEL
makeSignIn-1.0.0.dist-info/top_level.txt
makeSignIn-1.0.0.dist-info/RECORD
